{
  "monitoring": {
    "wattmeter": false
  },
  "network_adapters": [
    {
      "device": "eth0",
      "enabled": true,
      "interface": "Ethernet",
      "mac": "44:a8:42:16:69:da"
    },
    {
      "device": "eth1",
      "enabled": true,
      "interface": "Ethernet",
      "mac": "44:a8:42:16:69:dc"
    }
  ],
  "node_name": "c47",
  "node_type": "compute_haswell",
  "supported_job_types": {
    "besteffort": false,
    "deploy": true,
    "virtual": "ivt"
  },
  "type": "node",
  "uid": "b3d783a9-9fc3-4670-9d8e-5a6061808251"
}